glaft/__init__.py
glaft/georaster.py
glaft/metrics.py
glaft/preprocess.py
glaft-1.0.0.dist-info/LICENSE
glaft-1.0.0.dist-info/METADATA
glaft-1.0.0.dist-info/WHEEL
glaft-1.0.0.dist-info/top_level.txt
glaft-1.0.0.dist-info/RECORD
