Metadata-Version: 2.1
Name: glaft
Version: 1.0.0
Summary: GLAFT evaluates the quality of glacier velocity maps using statistics and physics based metrics.
Home-page: https://github.com/whyjz/GLAFT.git
Author: The GLAFT team
Author-email: whyjz@berkeley.edu
Maintainer: Whyjay Zheng
Maintainer-email: whyjz@berkeley.edu
License: MIT
Classifier: Programming Language :: Python :: 3
Classifier: License :: OSI Approved :: MIT License
Classifier: Operating System :: OS Independent
Classifier: Development Status :: 2 - Pre-Alpha
Classifier: Intended Audience :: Education
Classifier: Intended Audience :: Science/Research
Classifier: Topic :: Scientific/Engineering
Classifier: Topic :: Scientific/Engineering :: GIS
Classifier: Topic :: Scientific/Engineering :: Image Processing
Classifier: Topic :: Scientific/Engineering :: Physics
Requires-Python: >= 3.7
License-File: LICENSE
Requires-Dist: cmcrameri
Requires-Dist: geopandas
Requires-Dist: matplotlib
Requires-Dist: numpy
Requires-Dist: rasterio
Requires-Dist: scikit-learn
Requires-Dist: scipy
Requires-Dist: shapely
